exponent_server_sdk_async-2.1.7.dist-info/METADATA
exponent_server_sdk_async-2.1.7.dist-info/WHEEL
exponent_server_sdk_async-2.1.7.dist-info/licenses/LICENSE
exponent_server_sdk_async/__init__.py
exponent_server_sdk_async/main.py
exponent_server_sdk_async-2.1.7.dist-info/RECORD
