Metadata-Version: 2.1
Name: exponent_server_sdk_async
Version: 2.1.7
Summary: Expo Server SDK for Python async
Keywords: expo,sdk,async,push notifications
Author-Email: =?utf-8?q?Bahad=C4=B1r_Araz?= <bahadiraraz@protonmail.com>, Expo Team <exponent.team@gmail.com>
License: MIT
Project-URL: Homepage, https://github.com/Learnity-AI/expo-server-sdk-python-async
Requires-Python: >=3.12
Requires-Dist: six
Requires-Dist: httpx>=0.27.0
Requires-Dist: loguru>=0.7.2
Requires-Dist: python-dotenv>=1.0.1
